unicodec/__init__.py
unicodec/bom_encoding.py
unicodec/entities.py
unicodec/errors.py
unicodec/html_encoding.py
unicodec/http_encoding.py
unicodec/main.py
unicodec/normalization.py
unicodec/py.typed
unicodec/xml_encoding.py
unicodec-0.2.0.dist-info/licenses/LICENSE
unicodec-0.2.0.dist-info/METADATA
unicodec-0.2.0.dist-info/WHEEL
unicodec-0.2.0.dist-info/top_level.txt
unicodec-0.2.0.dist-info/RECORD
